examples/__init__.py
frlearn/__init__.py
frlearn/_version.py
frlearn/array_functions.py
frlearn/base.py
frlearn/classifiers.py
frlearn/data_descriptors.py
frlearn/dispersion_measures.py
frlearn/feature_preprocessors.py
frlearn/instance_preprocessors.py
frlearn/location_measures.py
frlearn/neighbour_search_methods.py
frlearn/parametrisations.py
frlearn/regressors.py
frlearn/t_norms.py
frlearn/transformations.py
frlearn/vector_size_measures.py
frlearn/weights.py
frlearn/neighbours/__init__.py
frlearn/neighbours/classifiers.py
frlearn/neighbours/data_descriptors.py
frlearn/neighbours/feature_preprocessors.py
frlearn/neighbours/instance_preprocessors.py
frlearn/neighbours/neighbour_search_methods.py
frlearn/neighbours/regressors.py
frlearn/neighbours/utilities.py
frlearn/neighbours/tests/__init__.py
frlearn/neighbours/tests/test_neighbours.py
frlearn/networks/__init__.py
frlearn/networks/feature_preprocessors.py
frlearn/networks/layers.py
frlearn/statistics/__init__.py
frlearn/statistics/data_descriptors.py
frlearn/statistics/dispersion_measures.py
frlearn/statistics/feature_preprocessors.py
frlearn/statistics/location_measures.py
frlearn/support_vectors/__init__.py
frlearn/support_vectors/data_descriptors.py
frlearn/tests/__init__.py
frlearn/tests/test_common.py
frlearn/trees/__init__.py
frlearn/trees/data_descriptors.py
frlearn/uncategorised/__init__.py
frlearn/uncategorised/array_functions.py
frlearn/uncategorised/feature_preprocessors.py
frlearn/uncategorised/parametrisations.py
frlearn/uncategorised/quantifiers.py
frlearn/uncategorised/t_norms.py
frlearn/uncategorised/transformations.py
frlearn/uncategorised/utilities.py
frlearn/uncategorised/vector_size_measures.py
frlearn/uncategorised/weights.py
frlearn/uncategorised/tests/__init__.py
frlearn/uncategorised/tests/test_uncategorised.py
fuzzy_rough_learn-0.2.2.dist-info/LICENSE
fuzzy_rough_learn-0.2.2.dist-info/METADATA
fuzzy_rough_learn-0.2.2.dist-info/WHEEL
fuzzy_rough_learn-0.2.2.dist-info/top_level.txt
fuzzy_rough_learn-0.2.2.dist-info/RECORD
