Metadata-Version: 2.1
Name: fuzzy-rough-learn
Version: 0.2.2
Summary: A library of fuzzy rough machine learning algorithms and data descriptors.
Home-page: https://github.com/oulenz/fuzzy-rough-learn
Download-URL: https://github.com/oulenz/fuzzy-rough-learn
Maintainer: Oliver Urs Lenz
Maintainer-email: oliver.urs.lenz@gmail.com
License: MIT
Classifier: Intended Audience :: Science/Research
Classifier: Intended Audience :: Developers
Classifier: License :: OSI Approved
Classifier: Topic :: Software Development
Classifier: Topic :: Scientific/Engineering
Classifier: Operating System :: Microsoft :: Windows
Classifier: Operating System :: POSIX
Classifier: Operating System :: Unix
Classifier: Programming Language :: Python :: 3.7
License-File: LICENSE
Requires-Dist: numpy (>=1.17.0)
Requires-Dist: scipy (>=1.1.0)
Requires-Dist: scikit-learn (>=0.24.0)
Provides-Extra: docs
Requires-Dist: sphinx ; extra == 'docs'
Requires-Dist: sphinx-gallery ; extra == 'docs'
Requires-Dist: sphinx-rtd-theme (>=0.5.0rc2) ; extra == 'docs'
Requires-Dist: numpydoc ; extra == 'docs'
Requires-Dist: matplotlib ; extra == 'docs'
Provides-Extra: full
Requires-Dist: tensorflow (>=2.2.0) ; extra == 'full'
Requires-Dist: eif (>=2.0.0) ; extra == 'full'
Provides-Extra: tests
Requires-Dist: pytest ; extra == 'tests'
Requires-Dist: pytest-cov ; extra == 'tests'
